pypulseq/__init__.py
pypulseq/add_gradients.py
pypulseq/add_ramps.py
pypulseq/align.py
pypulseq/block_to_events.py
pypulseq/calc_duration.py
pypulseq/calc_ramp.py
pypulseq/calc_rf_bandwidth.py
pypulseq/calc_rf_center.py
pypulseq/check_timing.py
pypulseq/compress_shape.py
pypulseq/convert.py
pypulseq/decompress_shape.py
pypulseq/event_lib.py
pypulseq/make_adc.py
pypulseq/make_adiabatic_pulse.py
pypulseq/make_arbitrary_grad.py
pypulseq/make_arbitrary_rf.py
pypulseq/make_block_pulse.py
pypulseq/make_delay.py
pypulseq/make_digital_output_pulse.py
pypulseq/make_extended_trapezoid.py
pypulseq/make_extended_trapezoid_area.py
pypulseq/make_gauss_pulse.py
pypulseq/make_label.py
pypulseq/make_sigpy_pulse.py
pypulseq/make_sinc_pulse.py
pypulseq/make_soft_delay.py
pypulseq/make_trapezoid.py
pypulseq/make_trigger.py
pypulseq/opts.py
pypulseq/points_to_waveform.py
pypulseq/rotate.py
pypulseq/scale_grad.py
pypulseq/sigpy_pulse_opts.py
pypulseq/split_gradient.py
pypulseq/split_gradient_at.py
pypulseq/supported_labels_rf_use.py
pypulseq/traj_to_grad.py
pypulseq/SAR/SAR_calc.py
pypulseq/SAR/__init__.py
pypulseq/Sequence/__init__.py
pypulseq/Sequence/block.py
pypulseq/Sequence/calc_grad_spectrum.py
pypulseq/Sequence/calc_pns.py
pypulseq/Sequence/ext_test_report.py
pypulseq/Sequence/install.py
pypulseq/Sequence/parula.py
pypulseq/Sequence/read_seq.py
pypulseq/Sequence/sequence.py
pypulseq/Sequence/write_seq.py
pypulseq/utils/__init__.py
pypulseq/utils/cumsum.py
pypulseq/utils/paper_plot.py
pypulseq/utils/safe_pns_prediction.py
pypulseq/utils/seq_plot.py
pypulseq/utils/tracing.py
pypulseq/utils/siemens/__init__.py
pypulseq/utils/siemens/asc_to_hw.py
pypulseq/utils/siemens/readasc.py
pypulseq-1.5.0.post1.dist-info/licenses/LICENSE
pypulseq-1.5.0.post1.dist-info/METADATA
pypulseq-1.5.0.post1.dist-info/WHEEL
pypulseq-1.5.0.post1.dist-info/top_level.txt
pypulseq-1.5.0.post1.dist-info/RECORD
