Metadata-Version: 2.4
Name: pypulseq
Version: 1.5.0.post1
Summary: Pulseq in Python
Author-email: Keerthi Sravan Ravi <ks3621@columbia.edu>
Maintainer: Bilal Tasdelen, Frank Ziljstra, Patrick Schuenke, Sairam Geethanath, Matteo Cencini
License: MIT License
Project-URL: Homepage, https://github.com/imr-framework/pypulseq
Project-URL: Issues, https://github.com/imr-framework/pypulseq/issues
Project-URL: Documentation, https://pypulseq.readthedocs.io/en/latest/
Classifier: Programming Language :: Python :: 3
Classifier: License :: OSI Approved :: MIT License
Classifier: Operating System :: OS Independent
Requires-Python: >=3.8
License-File: LICENSE
Requires-Dist: coverage>=6.2
Requires-Dist: matplotlib>=3.5.2
Requires-Dist: numpy>=1.19.5
Requires-Dist: scipy>=1.8.1
Provides-Extra: sigpy
Requires-Dist: sigpy>=0.1.26; extra == "sigpy"
Provides-Extra: mplcursors
Requires-Dist: mplcursors; extra == "mplcursors"
Provides-Extra: qt
Requires-Dist: PySide6; extra == "qt"
Provides-Extra: test
Requires-Dist: coverage; extra == "test"
Requires-Dist: codecov; extra == "test"
Requires-Dist: pre-commit; extra == "test"
Requires-Dist: pytest; extra == "test"
Requires-Dist: pytest-cov<6.1; extra == "test"
Requires-Dist: pytest-xdist; extra == "test"
Provides-Extra: docs
Requires-Dist: sphinx; extra == "docs"
Requires-Dist: jinja2; extra == "docs"
Requires-Dist: furo; extra == "docs"
Requires-Dist: recommonmark; extra == "docs"
Dynamic: license-file
